bloxapi/__init__.py
bloxapi/bloxapi.py
bloxapi-0.1.7.dist-info/licenses/LICENSE
bloxapi-0.1.7.dist-info/METADATA
bloxapi-0.1.7.dist-info/WHEEL
bloxapi-0.1.7.dist-info/top_level.txt
bloxapi-0.1.7.dist-info/RECORD
