Metadata-Version: 2.4
Name: bloxapi
Version: 0.1.7
Summary: Advanced roblox wrapper for the Roblox API.
Home-page: https://github.com/jmkdev/bloxapi
Author: jmkdev
Author-email: jmkdev <jmkdev@gmail.com>
Project-URL: Homepage, https://github.com/jmkdev/bloxapi
Project-URL: Bug Tracker, https://github.com/jmkdev/bloxapi/issues
Classifier: Development Status :: 3 - Alpha
Classifier: Intended Audience :: Developers
Classifier: License :: OSI Approved :: MIT License
Classifier: Operating System :: OS Independent
Classifier: Programming Language :: Python :: 3
Classifier: Programming Language :: Python :: 3.7
Classifier: Programming Language :: Python :: 3.8
Classifier: Programming Language :: Python :: 3.9
Classifier: Programming Language :: Python :: 3.10
Classifier: Programming Language :: Python :: 3.11
Requires-Python: >=3.7
License-File: LICENSE
Requires-Dist: discord.py>=2.0.0
Requires-Dist: requests>=2.25.0
Requires-Dist: pyautogui>=0.9.50
Requires-Dist: python-dotenv>=0.19.0
Requires-Dist: comtypes>=1.1.0
Requires-Dist: pycaw>=20220416
Requires-Dist: mss>=6.1.0
Requires-Dist: pynput>=1.7.0
Requires-Dist: pywin32>=227
Dynamic: author
Dynamic: home-page
Dynamic: license-file
Dynamic: requires-python
